enlaypy/__init__.py
enlaypy/client.py
enlaypy/errors.py
enlaypy-0.1.dist-info/METADATA
enlaypy-0.1.dist-info/WHEEL
enlaypy-0.1.dist-info/top_level.txt
enlaypy-0.1.dist-info/RECORD
