Metadata-Version: 2.1
Name: enlaypy
Version: 0.1
Summary: Enlay.io python package
Home-page: https://github.com/Artucuno/enlaypy
Author: Artucuno
Author-email: artucunov@gmail.com
License: MIT
Platform: UNKNOWN
Requires-Dist: requests
Requires-Dist: httpx
Requires-Dist: asyncio
